
{
  "items":[
    {"localName":"GS03",
      "displayName": "胶囊跳蛋",
      "deviceType":0,
      "isHotDevice":false,
      "isBleDevice": false,
      "madaCount":1,
      "isStrong":false,
      "isNewBroadcast":false,
      "isTelescoping":false
    },
    {"localName":"GS07",
      "displayName": "觅雅Miya",
      "deviceType":0,
      "isHotDevice":false,
      "isBleDevice": false,
      "madaCount":1,
      "isStrong":false,
      "isNewBroadcast":false,
      "isTelescoping":false
    },
    {"localName":"GS85",
      "displayName": "夏娜",
      "deviceType":0,
      "isHotDevice":false,
      "isBleDevice": false,
      "madaCount":1,
      "isStrong":false,
      "isNewBroadcast":false,
      "isTelescoping":false
    },
    {"localName":"GK10085",
      "displayName": "夏娜",
      "deviceType":0,
      "isHotDevice":false,
      "isBleDevice": true,
      "madaCount":1,
      "isStrong":false,
      "isNewBroadcast":false,
      "isTelescoping":false
    },
    {"localName":"GS02",
      "displayName": "超薄穿戴",
      "deviceType":0,
      "isHotDevice":false,
      "isBleDevice": false,
      "madaCount":1,
      "isStrong":false,
      "isNewBroadcast":false,
      "isTelescoping":false
    },
    {"localName":"GS10",
      "displayName": "贝壳穿戴",
      "deviceType":0,
      "isHotDevice":false,
      "isBleDevice": false,
      "madaCount":1,
      "isStrong":false,
      "isNewBroadcast":false,
      "isTelescoping":false
    },
    {"localName":"GS01",
      "displayName": "进阶后庭",
      "deviceType":0,
      "isHotDevice":false,
      "isBleDevice": false,
      "madaCount":1,
      "isStrong":false,
      "isNewBroadcast":false,
      "isTelescoping":false
    },
    {"localName":"GS08",
      "displayName": "线控双跳",
      "deviceType":1,
      "isHotDevice":false,
      "isBleDevice": false,
      "madaCount":2,
      "isStrong":false,
      "isNewBroadcast":false,
      "isTelescoping":false
    },
    {"localName":"GSA8",
      "displayName": "线控双跳",
      "deviceType":1,
      "isHotDevice":false,
      "isBleDevice": false,
      "madaCount":2,
      "isStrong":false,
      "isNewBroadcast":false,
      "isTelescoping":false
    },
    {"localName":"GS04",
      "displayName": "章鱼",
      "deviceType":0,
      "isHotDevice":false,
      "isBleDevice": false,
      "madaCount":1,
      "isStrong":false,
      "isNewBroadcast":false,
      "isTelescoping":false
    },
    {"localName":"GS17",
      "displayName": "胶囊口红",
      "deviceType":0,
      "isHotDevice":false,
      "isBleDevice": false,
      "madaCount":1,
      "isStrong":false,
      "isNewBroadcast":false,
      "isTelescoping":false
    },
    {"localName":"GS13",
      "displayName": "元气章鱼Mini",
      "deviceType":1,
      "isHotDevice":false,
      "isBleDevice": false,
      "madaCount":2,
      "isStrong":false,
      "isNewBroadcast":false,
      "isTelescoping":false
    },
    {"localName":"GS21",
      "displayName": "元气猫",
      "deviceType":0,
      "isHotDevice":false,
      "isBleDevice": false,
      "madaCount":1,
      "isStrong":false,
      "isNewBroadcast":false,
      "isTelescoping":false
    },
    {"localName":"GS22",
      "displayName": "幻影X",
      "deviceType":0,
      "isHotDevice":false,
      "isBleDevice": false,
      "madaCount":1,
      "isStrong":false,
      "isNewBroadcast":false,
      "isTelescoping":false
    },
    {"localName":"GS23",
      "displayName": "异次元1号",
      "deviceType":0,
      "isHotDevice":false,
      "isBleDevice": false,
      "madaCount":1,
      "isStrong":false,
      "isNewBroadcast":false,
      "isTelescoping":false
    },
    {"localName":"GS16",
      "displayName": "元气草莓",
      "deviceType":0,
      "isHotDevice":false,
      "isBleDevice": false,
      "madaCount":1,
      "isStrong":false,
      "isNewBroadcast":false,
      "isTelescoping":false
    },
    {"localName":"GS19",
      "displayName": "觅喜mini",
      "deviceType":0,
      "isHotDevice":false,
      "isBleDevice": false,
      "madaCount":1,
      "isStrong":false,
      "isNewBroadcast":false,
      "isTelescoping":false
    },
    {"localName":"GK03-080",
      "displayName": "胶囊跳蛋",
      "deviceType":0,
      "isHotDevice":false,
      "isBleDevice": true,
      "madaCount":1,
      "isStrong":false,
      "isNewBroadcast":false,
      "isTelescoping":false
    },
    {"localName":"AS67",
      "displayName": "振动棒",
      "deviceType":1,
      "isHotDevice":false,
      "isBleDevice": true,
      "madaCount":2,
      "isStrong":false,
      "isNewBroadcast":false,
      "isTelescoping":false
    },
    {"localName":"AS90",
      "displayName": "飞机杯",
      "deviceType":2,
      "isHotDevice":false,
      "isBleDevice": true,
      "madaCount":1,
      "isStrong":false,
      "isNewBroadcast":false,
      "isTelescoping":false
    },
    {"localName":"EJX-Para01",
      "displayName": "觅雅Miya",
      "deviceType":0,
      "isHotDevice":false,
      "isBleDevice": true,
      "madaCount":1,
      "isStrong":false,
      "isNewBroadcast":false,
      "isTelescoping":false
    },
    {"localName":"TFG1",
      "displayName": "极光飞机杯",
      "deviceType":2,
      "isHotDevice":false,
      "isBleDevice": true,
      "madaCount":1,
      "isStrong":false,
      "isNewBroadcast":false,
      "isTelescoping":false
    },
    {"localName":"GK27",
      "displayName": "小钢炮Cannon-GT",
      "deviceType":0,
      "isHotDevice":false,
      "isBleDevice": true,
      "madaCount":1,
      "isStrong":false,
      "isNewBroadcast":false,
      "isTelescoping":false
    },
    {"localName":"GK25",
      "displayName": "幻影PLUS",
      "deviceType":2,
      "isHotDevice":false,
      "isBleDevice": true,
      "madaCount":1,
      "isStrong":false,
      "isNewBroadcast":false,
      "isTelescoping":false
    },
    {"localName":"AC695X_1(BLE)",
      "displayName": "幻视vision",
      "deviceType":2,
      "isHotDevice":false,
      "isBleDevice": true,
      "madaCount":1,
      "isStrong":false,
      "isNewBroadcast":false,
      "isTelescoping":false
    },
    {"localName":"V415",
      "displayName": "星云",
      "deviceType":0,
      "isHotDevice":false,
      "isBleDevice": true,
      "madaCount":1,
      "isStrong":false,
      "isNewBroadcast":false,
      "isTelescoping":false
    },
    {"localName":"GK22",
      "displayName": "觅糖 META",
      "deviceType":0,
      "isHotDevice":false,
      "isBleDevice": false,
      "madaCount":1,
      "isStrong":false,
      "isNewBroadcast":false,
      "isTelescoping":false
    },
    {"localName":"G29B",
      "displayName": "小魔盒",
      "deviceType":0,
      "isHotDevice":false,
      "isBleDevice": false,
      "madaCount":1,
      "isStrong":false,
      "isNewBroadcast":false,
      "isTelescoping":false
    },
    {"localName":"GA25",
      "displayName": "丁丁穿戴",
      "deviceType":0,
      "isHotDevice":false,
      "isBleDevice": false,
      "madaCount":1,
      "isStrong":false,
      "isNewBroadcast":false,
      "isTelescoping":false
    },
    {"localName":"G29A",
      "displayName": "小魔方",
      "deviceType":0,
      "isHotDevice":false,
      "isBleDevice": false,
      "madaCount":1,
      "isStrong":false,
      "isNewBroadcast":false,
      "isTelescoping":false
    },
    {"localName":"GA23",
      "displayName": "小鲸鱼",
      "deviceType":0,
      "isHotDevice":false,
      "isBleDevice": false,
      "madaCount":1,
      "isStrong":false,
      "isNewBroadcast":false,
      "isTelescoping":false
    },
    {"localName":"GA26",
      "displayName": "小豌豆pea",
      "deviceType":0,
      "isHotDevice":false,
      "isBleDevice": false,
      "madaCount":1,
      "isStrong":false,
      "isNewBroadcast":false,
      "isTelescoping":false
    },
    {"localName":"GX85",
      "displayName": "夏娜",
      "deviceType":0,
      "isHotDevice":false,
      "isBleDevice": true,
      "madaCount":1,
      "isStrong":false,
      "isNewBroadcast":false,
      "isTelescoping":false
    },
    {"localName":"GX07",
      "displayName": "觅雅",
      "deviceType":0,
      "isHotDevice":false,
      "isBleDevice": true,
      "madaCount":1,
      "isStrong":false,
      "isNewBroadcast":false,
      "isTelescoping":false
    },
    {"localName":"GX17",
      "displayName": "胶囊口红",
      "deviceType":0,
      "isHotDevice":false,
      "isBleDevice": true,
      "madaCount":1,
      "isStrong":false,
      "isNewBroadcast":false,
      "isTelescoping":false
    },
    {"localName":"GX21",
      "displayName": "元气猫",
      "deviceType":0,
      "isHotDevice":false,
      "isBleDevice": true,
      "madaCount":1,
      "isStrong":false,
      "isNewBroadcast":false,
      "isTelescoping":false
    },
    {"localName":"GX33",
      "displayName": "异次元1号",
      "deviceType":0,
      "isHotDevice":false,
      "isBleDevice": true,
      "madaCount":1,
      "isStrong":false,
      "isNewBroadcast":false,
      "isTelescoping":false
    },
    {"localName":"GX22",
      "displayName": "幻影X",
      "deviceType":0,
      "isHotDevice":false,
      "isBleDevice": true,
      "madaCount":1,
      "isStrong":false,
      "isNewBroadcast":false,
      "isTelescoping":false
    },
    {"localName":"GX16",
      "displayName": "元气草莓",
      "deviceType":0,
      "isHotDevice":false,
      "isBleDevice": true,
      "madaCount":1,
      "isStrong":false,
      "isNewBroadcast":false,
      "isTelescoping":false
    },
    {"localName":"GX29",
      "displayName": "小魔盒",
      "deviceType":0,
      "isHotDevice":false,
      "isBleDevice": true,
      "madaCount":1,
      "isStrong":false,
      "isNewBroadcast":false,
      "isTelescoping":false
    },
    {"localName":"GX23",
      "displayName": "小鲸鱼",
      "deviceType":0,
      "isHotDevice":false,
      "isBleDevice": true,
      "madaCount":1,
      "isStrong":false,
      "isNewBroadcast":false,
      "isTelescoping":false
    },
    {"localName":"GX25",
      "displayName": "快乐震动器",
      "deviceType":0,
      "isHotDevice":false,
      "isBleDevice": true,
      "madaCount":1,
      "isStrong":false,
      "isNewBroadcast":false,
      "isTelescoping":false
    },
    {"localName":"GX26",
      "displayName": "小豌豆",
      "deviceType":0,
      "isHotDevice":false,
      "isBleDevice": true,
      "madaCount":1,
      "isStrong":false,
      "isNewBroadcast":false,
      "isTelescoping":false
    },
    {"localName":"GK03",
      "displayName": "胶囊跳蛋",
      "deviceType":0,
      "isHotDevice":false,
      "isBleDevice": true,
      "madaCount":1,
      "isStrong":false,
      "isNewBroadcast":false,
      "isTelescoping":false
    },
    {"localName":"GX36",
      "displayName": "电击跳蛋",
      "deviceType":3,
      "isHotDevice":false,
      "isBleDevice": true,
      "madaCount":1,
      "isStrong":false,
      "isNewBroadcast":false,
      "isTelescoping":false
    },
    {"localName":"GX39",
      "displayName": "雪糕筒miniAV棒",
      "deviceType":0,
      "isHotDevice":false,
      "isBleDevice": true,
      "madaCount":1,
      "isStrong":false,
      "isNewBroadcast":false,
      "isTelescoping":false
    },
    {"localName":"G311",
      "displayName": "芙蕾雅",
      "deviceType":4,
      "isHotDevice":false,
      "isBleDevice": true,
      "madaCount":2,
      "isStrong":false,
      "isNewBroadcast":false,
      "isTelescoping":false
    },
    {"localName":"GK36",
      "displayName": "小捣蛋",
      "deviceType":3,
      "isHotDevice":false,
      "isBleDevice": true,
      "madaCount":1,
      "isStrong":false,
      "isNewBroadcast":false,
      "isTelescoping":false
    },
    {"localName":"G317",
      "displayName": "渣古飞机杯",
      "deviceType":1,
      "isHotDevice":false,
      "isBleDevice": true,
      "madaCount":2,
      "isStrong":true,
      "isNewBroadcast":false,
      "isTelescoping":false
    },
    {"localName":"G312",
      "displayName": "机甲-原主飞机杯",
      "deviceType":1,
      "isHotDevice":false,
      "isBleDevice": true,
      "madaCount":2,
      "isStrong":true,
      "isNewBroadcast":false,
      "isTelescoping":false
    },
    {"localName":"G302",
      "displayName": "小恶魔",
      "deviceType":1,
      "isHotDevice":true,
      "isBleDevice": true,
      "madaCount":2,
      "isStrong":false,
      "isNewBroadcast":false,
      "isTelescoping":false
    },
    {"localName":"G321",
      "displayName": "mini雪糕筒",
      "deviceType":0,
      "isHotDevice":false,
      "isBleDevice": true,
      "madaCount":1,
      "isStrong":false,
      "isNewBroadcast":false,
      "isTelescoping":false
    },
    {"localName":"G304",
      "displayName": "希娅项圈",
      "deviceType":0,
      "isHotDevice":false,
      "isBleDevice": true,
      "madaCount":1,
      "isStrong":false,
      "isNewBroadcast":false,
      "isTelescoping":false
    },
    {"localName":"G320",
      "displayName": "雅典娜\/悦娜",
      "deviceType":1,
      "isHotDevice":false,
      "isBleDevice": true,
      "madaCount":2,
      "isStrong":false,
      "isNewBroadcast":false,
      "isTelescoping":true
    },
    {"localName":"K320",
      "displayName": "雅典娜 Vib",
      "deviceType":1,
      "isHotDevice":false,
      "isBleDevice": true,
      "madaCount":2,
      "isStrong":false,
      "isNewBroadcast":false,
      "isTelescoping":true
    },
    {"localName":"G314",
      "displayName": "元气章鱼II",
      "deviceType":1,
      "isHotDevice":true,
      "isBleDevice": true,
      "madaCount":2,
      "isStrong":false,
      "isNewBroadcast":false,
      "isTelescoping":false
    },
    {"localName":"G315",
      "displayName": "独角兽",
      "deviceType":1,
      "isHotDevice":true,
      "isBleDevice": true,
      "madaCount":2,
      "isStrong":false,
      "isNewBroadcast":false,
      "isTelescoping":false
    },
    {"localName":"G307",
      "displayName": "蜂后炮机",
      "deviceType":1,
      "isHotDevice":false,
      "isBleDevice": true,
      "madaCount":2,
      "isStrong":false,
      "isNewBroadcast":false,
      "isTelescoping":true
    },
    {"localName":"K311",
      "displayName": "芙蕾雅",
      "deviceType":4,
      "isHotDevice":false,
      "isBleDevice": true,
      "madaCount":2,
      "isStrong":false,
      "isNewBroadcast":false,
      "isTelescoping":false
    },
    {"localName":"G336",
      "displayName": "元气鸟二代",
      "deviceType":0,
      "isHotDevice":false,
      "isBleDevice": true,
      "madaCount":1,
      "isStrong":false,
      "isNewBroadcast":false,
      "isTelescoping":false
    },
    {"localName":"G331",
      "displayName": "八爪鱼龟头按摩器",
      "deviceType":0,
      "isHotDevice":false,
      "isBleDevice": true,
      "madaCount":1,
      "isStrong":false,
      "isNewBroadcast":false,
      "isTelescoping":false
    },
    {"localName":"G326",
      "displayName": "爱丽丝",
      "deviceType":0,
      "isHotDevice":false,
      "isBleDevice": true,
      "madaCount":1,
      "isStrong":false,
      "isNewBroadcast":false,
      "isTelescoping":false
    },
    {"localName":"G335",
      "displayName": "独角兽肛塞",
      "deviceType":0,
      "isHotDevice":false,
      "isBleDevice": true,
      "madaCount":1,
      "isStrong":false,
      "isNewBroadcast":false,
      "isTelescoping":false
    },
    {"localName":"GXA3",
      "displayName": "鲸鱼测试",
      "deviceType":0,
      "isHotDevice":false,
      "isBleDevice": false,
      "madaCount":1,
      "isStrong":false,
      "isNewBroadcast":true,
      "isTelescoping":false
    },
    {"localName":"A456",
      "displayName": "艾斯",
      "deviceType":0,
      "isHotDevice":false,
      "isBleDevice": false,
      "madaCount":1,
      "isStrong":false,
      "isNewBroadcast":false,
      "isTelescoping":false
    },
    {"localName":"G341",
      "displayName": "艾斯",
      "deviceType":0,
      "isHotDevice":false,
      "isBleDevice": true,
      "madaCount":1,
      "isStrong":false,
      "isNewBroadcast":false,
      "isTelescoping":false
    },
    {"localName":"G324",
      "displayName": "雅典娜脉冲",
      "deviceType":6,
      "isHotDevice":false,
      "isBleDevice": true,
      "madaCount":2,
      "isStrong":false,
      "isNewBroadcast":false,
      "isTelescoping":false
    },
    {"localName":"G339",
      "displayName": "犀牛前列腺按摩器",
      "deviceType":1,
      "isHotDevice":false,
      "isBleDevice": true,
      "madaCount":2,
      "isStrong":false,
      "isNewBroadcast":false,
      "isTelescoping":false
    },
    {"localName":"G350",
      "displayName": "元气鲸",
      "deviceType":5,
      "isHotDevice":false,
      "isBleDevice": true,
      "madaCount":1,
      "isStrong":false,
      "isNewBroadcast":false,
      "isTelescoping":false
    },
    {"localName":"G355",
      "displayName": "小萌龟",
      "deviceType":0,
      "isHotDevice":false,
      "isBleDevice": true,
      "madaCount":1,
      "isStrong":false,
      "isNewBroadcast":false,
      "isTelescoping":false
    },
    {"localName":"G349",
      "displayName": "小子弹",
      "deviceType":0,
      "isHotDevice":false,
      "isBleDevice": true,
      "madaCount":1,
      "isStrong":false,
      "isNewBroadcast":false,
      "isTelescoping":false
    },
    {"localName":"G354",
      "displayName": "双甲飞机杯",
      "deviceType":1,
      "isHotDevice":false,
      "isBleDevice": true,
      "madaCount":2,
      "isStrong":true,
      "isNewBroadcast":false,
      "isTelescoping":false
    },
    {"localName":"G303",
      "displayName": "小恐龙",
      "deviceType":6,
      "isHotDevice":false,
      "isBleDevice": true,
      "madaCount":2,
      "isStrong":false,
      "isNewBroadcast":false,
      "isTelescoping":false
    },
    {"localName":"G407",
      "displayName": "喜悦跳蛋",
      "deviceType":0,
      "isHotDevice":false,
      "isBleDevice": true,
      "madaCount":1,
      "isStrong":false,
      "isNewBroadcast":false,
      "isTelescoping":false
    },
    {"localName":"G204",
      "displayName": "保龄球",
      "deviceType":0,
      "isHotDevice":false,
      "isBleDevice": true,
      "madaCount":1,
      "isStrong":false,
      "isNewBroadcast":false,
      "isTelescoping":false
    },
    {"localName":"G171",
      "displayName": "觅心控制器",
      "deviceType":0,
      "isHotDevice":true,
      "isBleDevice": true,
      "madaCount":1,
      "isStrong":false,
      "isNewBroadcast":false,
      "isTelescoping":false
    },
    {"localName":"G12D",
      "displayName": "花潮笔",
      "deviceType":0,
      "isHotDevice":true,
      "isBleDevice": true,
      "madaCount":1,
      "isStrong":false,
      "isNewBroadcast":false,
      "isTelescoping":false
    },
    {"localName":"G12B",
      "displayName": "花潮笔",
      "deviceType":0,
      "isHotDevice":true,
      "isBleDevice": true,
      "madaCount":1,
      "isStrong":false,
      "isNewBroadcast":false,
      "isTelescoping":false
    },
    {"localName":"G123",
      "displayName": "花塞",
      "deviceType":0,
      "isHotDevice":false,
      "isBleDevice": true,
      "madaCount":1,
      "isStrong":false,
      "isNewBroadcast":false,
      "isTelescoping":false
    },
    {"localName":"G12Z",
      "displayName": "花季",
      "deviceType":1,
      "isHotDevice":true,
      "isBleDevice": true,
      "madaCount":2,
      "isStrong":false,
      "isNewBroadcast":false,
      "isTelescoping":false
    },
    {"localName":"G231",
      "displayName": "梦幻脉冲",
      "deviceType":7,
      "isHotDevice":false,
      "isBleDevice": true,
      "madaCount":1,
      "isStrong":false,
      "isNewBroadcast":false,
      "isTelescoping":false
    },
    {"localName":"G29C",
      "displayName": "小魔方",
      "deviceType":1,
      "isHotDevice":false,
      "isBleDevice": true,
      "madaCount":2,
      "isStrong":false,
      "isNewBroadcast":false,
      "isTelescoping":false
    },
    {"localName":"G29D",
      "displayName": "小粉饼",
      "deviceType":1,
      "isHotDevice":false,
      "isBleDevice": true,
      "madaCount":2,
      "isStrong":false,
      "isNewBroadcast":false,
      "isTelescoping":false
    },
    {"localName":"GKML",
      "displayName": "米莉",
      "deviceType":1,
      "isHotDevice":true,
      "isBleDevice": true,
      "madaCount":2,
      "isStrong":false,
      "isNewBroadcast":false,
      "isTelescoping":false
    },
    {"localName":"G348",
      "displayName": "犀牛后庭",
      "deviceType":1,
      "isHotDevice":false,
      "isBleDevice": true,
      "madaCount":2,
      "isStrong":false,
      "isNewBroadcast":false,
      "isTelescoping":false
    },
    {"localName":"G23A",
      "displayName": "梦幻振动",
      "deviceType":0,
      "isHotDevice":false,
      "isBleDevice": true,
      "madaCount":1,
      "isStrong":false,
      "isNewBroadcast":false,
      "isTelescoping":false
    },
    {"localName":"A073",
      "displayName": "喜悦跳蛋",
      "deviceType":0,
      "isHotDevice":false,
      "isBleDevice": true,
      "madaCount":1,
      "isStrong":false,
      "isNewBroadcast":false,
      "isTelescoping":false
    },
    {"localName":"GLMT",
      "displayName": "流氓兔",
      "deviceType":0,
      "isHotDevice":false,
      "isBleDevice": true,
      "madaCount":1,
      "isStrong":false,
      "isNewBroadcast":false,
      "isTelescoping":false
    },
    {"localName":"G912",
      "displayName": "甜甜圈",
      "deviceType":0,
      "isHotDevice":false,
      "isBleDevice": true,
      "madaCount":1,
      "isStrong":false,
      "isNewBroadcast":false,
      "isTelescoping":false
    },
    {"localName":"G913",
      "displayName": "独角兽二代",
      "deviceType":1,
      "isHotDevice":false,
      "isBleDevice": true,
      "madaCount":2,
      "isStrong":false,
      "isNewBroadcast":false,
      "isTelescoping":false
    },
    {"localName":"G213",
      "displayName": "魅影",
      "deviceType":1,
      "isHotDevice":true,
      "isBleDevice": true,
      "madaCount":2,
      "isStrong":false,
      "isNewBroadcast":false,
      "isTelescoping":false
    },
    {"localName":"TFF1",
      "displayName": "F1飞机杯",
      "deviceType":1,
      "isHotDevice":false,
      "isBleDevice": true,
      "madaCount":2,
      "isStrong":false,
      "isNewBroadcast":false,
      "isTelescoping":false
    },
    {"localName":"G20B",
      "displayName": "芭蕾震动棒",
      "deviceType":0,
      "isHotDevice":true,
      "isBleDevice": true,
      "madaCount":1,
      "isStrong":false,
      "isNewBroadcast":false,
      "isTelescoping":false
    },
    {"localName":"K112",
      "displayName": "甜甜圈",
      "deviceType":0,
      "isHotDevice":false,
      "isBleDevice": true,
      "madaCount":1,
      "isStrong":false,
      "isNewBroadcast":false,
      "isTelescoping":false
    },
    {"localName":"K113",
      "displayName": "独角兽二代",
      "deviceType":1,
      "isHotDevice":false,
      "isBleDevice": true,
      "madaCount":2,
      "isStrong":false,
      "isNewBroadcast":false,
      "isTelescoping":false
    },
    {"localName":"G202",
      "displayName": "调情笔",
      "deviceType":0,
      "isHotDevice":false,
      "isBleDevice": true,
      "madaCount":1,
      "isStrong":false,
      "isNewBroadcast":false,
      "isTelescoping":false
    },
    {"localName":"K118",
      "displayName": "红丸",
      "deviceType":0,
      "isHotDevice":false,
      "isBleDevice": true,
      "madaCount":1,
      "isStrong":false,
      "isNewBroadcast":false,
      "isTelescoping":false
    },
    {"localName":"K107",
      "displayName": "赛博朋克飞机杯",
      "deviceType":0,
      "isHotDevice":false,
      "isBleDevice": true,
      "madaCount":1,
      "isStrong":false,
      "isNewBroadcast":false,
      "isTelescoping":false
    },
    {"localName":"G203",
      "displayName": "元气萌宠",
      "deviceType":0,
      "isHotDevice":false,
      "isBleDevice": true,
      "madaCount":1,
      "isStrong":false,
      "isNewBroadcast":false,
      "isTelescoping":false
    },
    {"localName":"WSXK",
      "displayName": "Starry Sky CUP",
      "deviceType":2,
      "isHotDevice":false,
      "isBleDevice": true,
      "madaCount":1,
      "isStrong":false,
      "isNewBroadcast":false,
      "isTelescoping":false
    },
    {"localName":"G228",
      "displayName": "小海豚",
      "deviceType":1,
      "isHotDevice":true,
      "isBleDevice": true,
      "madaCount":2,
      "isStrong":false,
      "isNewBroadcast":false,
      "isTelescoping":false
    },
    {"localName":"G310",
      "displayName": "权杖AV棒",
      "deviceType":1,
      "isHotDevice":true,
      "isBleDevice": true,
      "madaCount":2,
      "isStrong":false,
      "isNewBroadcast":false,
      "isTelescoping":false
    },
    {"localName":"TXHL",
      "displayName": "小葫芦跳蛋",
      "deviceType":0,
      "isHotDevice":false,
      "isBleDevice": true,
      "madaCount":1,
      "isStrong":false,
      "isNewBroadcast":false,
      "isTelescoping":false
    },
    {"localName":"TXMM",
      "displayName": "小猫咪",
      "deviceType":0,
      "isHotDevice":false,
      "isBleDevice": true,
      "madaCount":1,
      "isStrong":false,
      "isNewBroadcast":false,
      "isTelescoping":false
    },
    {"localName":"TXKL",
      "displayName": "小恐龙",
      "deviceType":0,
      "isHotDevice":false,
      "isBleDevice": true,
      "madaCount":1,
      "isStrong":false,
      "isNewBroadcast":false,
      "isTelescoping":false
    },
    {"localName":"K108",
      "displayName": "铃铛吮吸",
      "deviceType":0,
      "isHotDevice":false,
      "isBleDevice": true,
      "madaCount":1,
      "isStrong":false,
      "isNewBroadcast":false,
      "isTelescoping":false
    },
    {"localName":"K109",
      "displayName": "铃铛震动",
      "deviceType":0,
      "isHotDevice":false,
      "isBleDevice": true,
      "madaCount":1,
      "isStrong":false,
      "isNewBroadcast":false,
      "isTelescoping":false
    },
    {"localName":"D322",
      "displayName": "独角兽",
      "deviceType":8,
      "isHotDevice":false,
      "isBleDevice": true,
      "madaCount":3,
      "isStrong":false,
      "isNewBroadcast":false,
      "isTelescoping":false
    },
    {"localName":"KWL2",
      "displayName": "助勃器",
      "deviceType":0,
      "isHotDevice":false,
      "isBleDevice": true,
      "madaCount":1,
      "isStrong":false,
      "isNewBroadcast":false,
      "isTelescoping":false
    },
    {"localName":"TFHL",
      "displayName": "Gyoyo-G（指悦-小葫芦）",
      "deviceType":0,
      "isHotDevice":false,
      "isBleDevice": true,
      "madaCount":1,
      "isStrong":false,
      "isNewBroadcast":false,
      "isTelescoping":false
    },
    {"localName":"TFMM",
      "displayName": "Gyoyo（指悦）",
      "deviceType":0,
      "isHotDevice":false,
      "isBleDevice": true,
      "madaCount":1,
      "isStrong":false,
      "isNewBroadcast":false,
      "isTelescoping":false
    },
    {"localName":"TFKL",
      "displayName": "Gyoyo（指悦）",
      "deviceType":0,
      "isHotDevice":false,
      "isBleDevice": true,
      "madaCount":1,
      "isStrong":false,
      "isNewBroadcast":false,
      "isTelescoping":false
    },
    {"localName":"D402",
      "displayName": "新系列振动棒",
      "deviceType":1,
      "isHotDevice":false,
      "isBleDevice": true,
      "madaCount":2,
      "isStrong":false,
      "isNewBroadcast":false,
      "isTelescoping":false
    },
    {"localName":"G40A",
      "displayName": "新系列振动棒",
      "deviceType":1,
      "isHotDevice":false,
      "isBleDevice": true,
      "madaCount":2,
      "isStrong":false,
      "isNewBroadcast":false,
      "isTelescoping":false
    },
    {"localName":"G403",
      "displayName": "新系列振动棒",
      "deviceType":1,
      "isHotDevice":false,
      "isBleDevice": true,
      "madaCount":2,
      "isStrong":false,
      "isNewBroadcast":false,
      "isTelescoping":false
    },
    {"localName":"G43A",
      "displayName": "新系列振动棒",
      "deviceType":1,
      "isHotDevice":false,
      "isBleDevice": true,
      "madaCount":2,
      "isStrong":false,
      "isNewBroadcast":false,
      "isTelescoping":false
    },
    {"localName":"K120",
      "displayName": "小指棒",
      "deviceType":0,
      "isHotDevice":false,
      "isBleDevice": true,
      "madaCount":1,
      "isStrong":false,
      "isNewBroadcast":false,
      "isTelescoping":false
    },
    {"localName":"K12A",
      "displayName": "小指棒",
      "deviceType":0,
      "isHotDevice":false,
      "isBleDevice": true,
      "madaCount":1,
      "isStrong":false,
      "isNewBroadcast":false,
      "isTelescoping":false
    },
    {"localName":"K12B",
      "displayName": "小指棒",
      "deviceType":1,
      "isHotDevice":false,
      "isBleDevice": true,
      "madaCount":2,
      "isStrong":false,
      "isNewBroadcast":false,
      "isTelescoping":false
    },
    {"localName":"K12C",
      "displayName": "小指棒",
      "deviceType":0,
      "isHotDevice":false,
      "isBleDevice": true,
      "madaCount":1,
      "isStrong":false,
      "isNewBroadcast":false,
      "isTelescoping":false
    },
    {"localName":"K125",
      "displayName": "肌肉男",
      "deviceType":1,
      "isHotDevice":true,
      "isBleDevice": true,
      "madaCount":2,
      "isStrong":false,
      "isNewBroadcast":false,
      "isTelescoping":false
    },
    {"localName":"K119",
      "displayName": "羽毛点潮笔",
      "deviceType":0,
      "isHotDevice":true,
      "isBleDevice": true,
      "madaCount":1,
      "isStrong":false,
      "isNewBroadcast":false,
      "isTelescoping":false
    },
    {"localName":"LL18",
      "displayName": "觅糖",
      "deviceType":0,
      "isHotDevice":false,
      "isBleDevice": false,
      "madaCount":1,
      "isStrong":false,
      "isNewBroadcast":false,
      "isTelescoping":false
    },
    {"localName":"D358",
      "displayName": "皇后AV棒",
      "deviceType":8,
      "isHotDevice":true,
      "isBleDevice": true,
      "madaCount":3,
      "isStrong":false,
      "isNewBroadcast":false,
      "isTelescoping":false
    },
    {"localName":"K099",
      "displayName": "觅欢",
      "deviceType":8,
      "isHotDevice":true,
      "isBleDevice": true,
      "madaCount":3,
      "isStrong":false,
      "isNewBroadcast":false,
      "isTelescoping":false
    },
    {"localName":"C32S",
      "displayName": "肌肉男USB",
      "deviceType":0,
      "isHotDevice":true,
      "isBleDevice": true,
      "madaCount":1,
      "isStrong":false,
      "isNewBroadcast":false,
      "isTelescoping":false
    },
    {"localName":"K097",
      "displayName": "觅爱-伸缩",
      "deviceType":8,
      "isHotDevice":true,
      "isBleDevice": true,
      "madaCount":3,
      "isStrong":false,
      "isNewBroadcast":false,
      "isTelescoping":false
    },
    {"localName":"K97A",
      "displayName": "觅爱-转珠",
      "deviceType":8,
      "isHotDevice":false,
      "isBleDevice": true,
      "madaCount":3,
      "isStrong":false,
      "isNewBroadcast":false,
      "isTelescoping":false
    },
    {"localName":"K098",
      "displayName": "觅悦-伸缩",
      "deviceType":8,
      "isHotDevice":true,
      "isBleDevice": true,
      "madaCount":3,
      "isStrong":false,
      "isNewBroadcast":false,
      "isTelescoping":false
    },
    {"localName":"K98A",
      "displayName": "觅悦-震动",
      "deviceType":1,
      "isHotDevice":true,
      "isBleDevice": true,
      "madaCount":2,
      "isStrong":false,
      "isNewBroadcast":false,
      "isTelescoping":false
    },
    {"localName":"GCDB",
      "displayName": "能量盒",
      "deviceType":1,
      "isHotDevice":false,
      "isBleDevice": true,
      "madaCount":2,
      "isStrong":false,
      "isNewBroadcast":false,
      "isTelescoping":false
    },
    {"localName":"K901",
      "displayName": "阿尔黛吮吸跳蛋",
      "deviceType":1,
      "isHotDevice":false,
      "isBleDevice": true,
      "madaCount":2,
      "isStrong":false,
      "isNewBroadcast":false,
      "isTelescoping":false
    },
    {"localName":"G901",
      "displayName": "阿尔黛震动跳蛋",
      "deviceType":1,
      "isHotDevice":false,
      "isBleDevice": true,
      "madaCount":2,
      "isStrong":false,
      "isNewBroadcast":false,
      "isTelescoping":false
    },
    {"localName":"U12A",
      "displayName": "肌肉男USB",
      "deviceType":1,
      "isHotDevice": true,
      "isBleDevice": true,
      "madaCount":2,
      "isStrong":false,
      "isNewBroadcast":false,
      "isTelescoping":false
    },
    {"localName":"K104",
      "displayName": "大白BayPro",
      "deviceType":2,
      "isHotDevice": false,
      "isBleDevice": true,
      "madaCount":1,
      "isStrong":false,
      "isNewBroadcast":false,
      "isTelescoping":false
    },
    {"localName":"G128",
      "displayName": "后庭战士",
      "deviceType":0,
      "isHotDevice": true,
      "isBleDevice": true,
      "madaCount":1,
      "isStrong":false,
      "isNewBroadcast":false,
      "isTelescoping":false
    },
    {"localName":"K128",
      "displayName": "F1龟头训练器",
      "deviceType":1,
      "isHotDevice": true,
      "isBleDevice": true,
      "madaCount":2,
      "isStrong":false,
      "isNewBroadcast":false,
      "isTelescoping":false
    },
    {"localName":"K121",
      "displayName": "烈焰红唇-吮吸",
      "deviceType":8,
      "isHotDevice":true,
      "isBleDevice": true,
      "madaCount":3,
      "isStrong":false,
      "isNewBroadcast":false,
      "isTelescoping":false
    },
    {"localName":"121A",
      "displayName": "烈焰红唇-舌舔",
      "deviceType":8,
      "isHotDevice":true,
      "isBleDevice": true,
      "madaCount":3,
      "isStrong":false,
      "isNewBroadcast":false,
      "isTelescoping":false
    },
    {"localName":"GX27",
      "displayName": "小钢炮Cannon-GT",
      "deviceType":0,
      "isHotDevice":false,
      "isBleDevice": true,
      "madaCount":1,
      "isStrong":false,
      "isNewBroadcast":false,
      "isTelescoping":false
    },
    {"localName":"K127",
      "displayName": "小海豚吮吸",
      "deviceType":1,
      "isHotDevice":true,
      "isBleDevice": true,
      "madaCount":2,
      "isStrong":false,
      "isNewBroadcast":false,
      "isTelescoping":false
    },
    {"localName":"JBDX",
      "displayName": "撩豆象",
      "deviceType":1,
      "isHotDevice":true,
      "isBleDevice": true,
      "madaCount":2,
      "isStrong":false,
      "isNewBroadcast":false,
      "isTelescoping":false
    },
    {"localName":"K143",
      "displayName": "蒂娜/琳娜",
      "deviceType":1,
      "isHotDevice":false,
      "isBleDevice": true,
      "madaCount":2,
      "isStrong":false,
      "isNewBroadcast":false,
      "isTelescoping":false
    },
    {"localName":"K135",
      "displayName": "小鲸鱼 Pro Max",
      "deviceType":0,
      "isHotDevice":false,
      "isBleDevice": true,
      "madaCount":1,
      "isStrong":false,
      "isNewBroadcast":false,
      "isTelescoping":false
    },
    {"localName":"K131",
      "displayName": "珍妮",
      "deviceType":1,
      "isHotDevice":false,
      "isBleDevice": true,
      "madaCount":2,
      "isStrong":false,
      "isNewBroadcast":false,
      "isTelescoping":false
    },
    {"localName":"121C",
      "displayName": "烈焰红唇-双震",
      "deviceType":1,
      "isHotDevice":true,
      "isBleDevice": true,
      "madaCount":2,
      "isStrong":false,
      "isNewBroadcast":false,
      "isTelescoping":false
    },
    {"localName":"121B",
      "displayName": "烈焰红唇 Pro Max",
      "deviceType":8,
      "isHotDevice":false,
      "isBleDevice": true,
      "madaCount":3,
      "isStrong":false,
      "isNewBroadcast":false,
      "isTelescoping":false
    },
    {"localName":"K133",
      "displayName": "桃心穿戴(Peach Air)",
      "deviceType":1,
      "isHotDevice":false,
      "isBleDevice": true,
      "madaCount":2,
      "isStrong":false,
      "isNewBroadcast":false,
      "isTelescoping":false
    },
    {"localName":"G127",
      "displayName": "小钢炮Air Pro",
      "deviceType":0,
      "isHotDevice":false,
      "isBleDevice": true,
      "madaCount":1,
      "isStrong":false,
      "isNewBroadcast":false,
      "isTelescoping":false
    },
    {"localName":"K138",
      "displayName": "小恐龙\/小狐狸",
      "deviceType":1,
      "isHotDevice":true,
      "isBleDevice": true,
      "madaCount":2,
      "isStrong":false,
      "isNewBroadcast":false,
      "isTelescoping":false
    },
    {"localName":"TF24",
      "displayName": "小鲜肉",
      "deviceType":0,
      "isHotDevice":false,
      "isBleDevice": true,
      "madaCount":1,
      "isStrong":false,
      "isNewBroadcast":false,
      "isTelescoping":false
    },
    {"localName":"G145",
      "displayName": "甜芯",
      "deviceType":1,
      "isHotDevice":true,
      "isBleDevice": true,
      "madaCount":2,
      "isStrong":false,
      "isNewBroadcast":false,
      "isTelescoping":false
    },
    {"localName":"G141",
      "displayName": "漫波玉露",
      "deviceType":8,
      "isHotDevice":false,
      "isBleDevice": true,
      "madaCount":3,
      "isStrong":false,
      "isNewBroadcast":false,
      "isTelescoping":false
    },
    {"localName":"G149",
      "displayName": "卡西娅",
      "deviceType":1,
      "isHotDevice":false,
      "isBleDevice": true,
      "madaCount":2,
      "isStrong":false,
      "isNewBroadcast":false,
      "isTelescoping":false
    },
    {"localName":"104B",
      "displayName": "大白Bay",
      "deviceType":0,
      "isHotDevice": false,
      "isBleDevice": true,
      "madaCount":1,
      "isStrong":false,
      "isNewBroadcast":false,
      "isTelescoping":false
    },
    {"localName":"G153",
      "displayName": "X舰飞机杯",
      "deviceType":1,
      "isHotDevice":false,
      "isBleDevice": true,
      "madaCount":2,
      "isStrong":true,
      "isNewBroadcast":false,
      "isTelescoping":false
    },
    {"localName":"G152",
      "displayName": "X舰",
      "deviceType":0,
      "isHotDevice":false,
      "isBleDevice": true,
      "madaCount":1,
      "isStrong":false,
      "isNewBroadcast":false,
      "isTelescoping":false
    },
    {"localName":"K134",
      "displayName": "桃心穿戴Pro (Peach Pro)",
      "deviceType":1,
      "isHotDevice":false,
      "isBleDevice": true,
      "madaCount":2,
      "isStrong":false,
      "isNewBroadcast":false,
      "isTelescoping":false
    },
    {"localName":"G146",
      "displayName": "月光宝盒",
      "deviceType":0,
      "isHotDevice":false,
      "isBleDevice": true,
      "madaCount":1,
      "isStrong":false,
      "isNewBroadcast":false,
      "isTelescoping":false
    },
    {"localName":"G157",
      "displayName": "指柔振动器",
      "deviceType":8,
      "isHotDevice":true,
      "isBleDevice": true,
      "madaCount":3,
      "isStrong":false,
      "isNewBroadcast":false,
      "isTelescoping":false
    },
    {"localName":"G150",
      "displayName": "如吻",
      "deviceType":2,
      "isHotDevice": false,
      "isBleDevice": true,
      "madaCount":1,
      "isStrong":false,
      "isNewBroadcast":false,
      "isTelescoping":false
    },
    {"localName":"G155",
      "displayName": "丁香",
      "deviceType":0,
      "isHotDevice":false,
      "isBleDevice": true,
      "madaCount":1,
      "isStrong":false,
      "isNewBroadcast":false,
      "isTelescoping":false
    },
    {"localName":"TFAX",
      "displayName": "爱心跳蛋",
      "deviceType":0,
      "isHotDevice":false,
      "isBleDevice": true,
      "madaCount":1,
      "isStrong":false,
      "isNewBroadcast":false,
      "isTelescoping":false
    },
    {"localName":"TFMN",
      "displayName": "迷你跳蛋",
      "deviceType":0,
      "isHotDevice":false,
      "isBleDevice": true,
      "madaCount":1,
      "isStrong":false,
      "isNewBroadcast":false,
      "isTelescoping":false
    },
    {"localName":"G162",
      "displayName": "美悦",
      "deviceType":8,
      "isHotDevice":false,
      "isBleDevice": true,
      "madaCount":3,
      "isStrong":false,
      "isNewBroadcast":false,
      "isTelescoping":false
    },
    {"localName":"G163",
      "displayName": "悦心",
      "deviceType":1,
      "isHotDevice":false,
      "isBleDevice": true,
      "madaCount":2,
      "isStrong":false,
      "isNewBroadcast":false,
      "isTelescoping":false
    },
    {"localName":"G164",
      "displayName": "梦露",
      "deviceType":1,
      "isHotDevice":false,
      "isBleDevice": true,
      "madaCount":2,
      "isStrong":false,
      "isNewBroadcast":false,
      "isTelescoping":false
    },
    {"localName":"G165",
      "displayName": "独角兽穿戴",
      "deviceType":1,
      "isHotDevice":false,
      "isBleDevice": true,
      "madaCount":2,
      "isStrong":false,
      "isNewBroadcast":false,
      "isTelescoping":false
    },
    {"localName":"G175",
      "displayName": "菲亚/尤利娅/汐吻",
      "deviceType":8,
      "isHotDevice":true,
      "isBleDevice": true,
      "madaCount":3,
      "isStrong":false,
      "isNewBroadcast":false,
      "isTelescoping":false
    },
    {"localName":"G169",
      "displayName": "糖果/糖丸",
      "deviceType":0,
      "isHotDevice":false,
      "isBleDevice": true,
      "madaCount":1,
      "isStrong":false,
      "isNewBroadcast":false,
      "isTelescoping":false,
      "isNewBle":true
    },
    {"localName":"G178",
      "displayName": "青柠",
      "deviceType":0,
      "isHotDevice":false,
      "isBleDevice": true,
      "madaCount":1,
      "isStrong":false,
      "isNewBroadcast":false,
      "isTelescoping":false
    },
    {"localName":"TF13",
      "displayName": "YY棒",
      "deviceType":1,
      "isHotDevice":false,
      "isBleDevice": true,
      "madaCount":2,
      "isStrong":false,
      "isNewBroadcast":false,
      "isTelescoping":true
    },
    {"localName":"CXMM",
      "displayName": "Gyoyo（指悦）",
      "deviceType":0,
      "isHotDevice":false,
      "isBleDevice": true,
      "madaCount":1,
      "isStrong":false,
      "isNewBroadcast":false,
      "isTelescoping":false
    },
    {"localName":"CXHL",
      "displayName": "Gyoyo-G（指悦-小葫芦）",
      "deviceType":0,
      "isHotDevice":false,
      "isBleDevice": true,
      "madaCount":1,
      "isStrong":false,
      "isNewBroadcast":false,
      "isTelescoping":false
    },
    {"localName":"CXKL",
      "displayName": "Gyoyo（指悦）",
      "deviceType":0,
      "isHotDevice":false,
      "isBleDevice": true,
      "madaCount":1,
      "isStrong":false,
      "isNewBroadcast":false,
      "isTelescoping":false
    },
    {"localName":"G176",
      "displayName": "大嘴花",
      "deviceType":8,
      "isHotDevice":false,
      "isBleDevice": true,
      "madaCount":3,
      "isStrong":false,
      "isNewBroadcast":false,
      "isTelescoping":false
    },
    {"localName":"G177",
      "displayName": "尤美",
      "deviceType":1,
      "isHotDevice":false,
      "isBleDevice": true,
      "madaCount":2,
      "isStrong":false,
      "isNewBroadcast":false,
      "isTelescoping":false
    },
    {"localName":"G320",
      "displayName": "雅典娜Vib",
      "deviceType":1,
      "isHotDevice":true,
      "isBleDevice": true,
      "madaCount":2,
      "isStrong":false,
      "isNewBroadcast":false,
      "isTelescoping":false
    },
    {"localName":"G190",
      "displayName": "大舌头",
      "deviceType":0,
      "isHotDevice":false,
      "isBleDevice": true,
      "madaCount":1,
      "isStrong":false,
      "isNewBroadcast":false,
      "isTelescoping":false
    },
    {"localName":"G181",
      "displayName": "口口棒",
      "deviceType":0,
      "isHotDevice":false,
      "isBleDevice": true,
      "madaCount":1,
      "isStrong":false,
      "isNewBroadcast":false,
      "isTelescoping":false
    },
    {"localName":"T402",
      "displayName": "红唇训练器",
      "deviceType":0,
      "isHotDevice":false,
      "isBleDevice": true,
      "madaCount":1,
      "isStrong":false,
      "isNewBroadcast":false,
      "isTelescoping":false
    },
    {"localName":"G188",
      "displayName": "小觅蜂",
      "deviceType":1,
      "isHotDevice":false,
      "isBleDevice": true,
      "madaCount":2,
      "isStrong":false,
      "isNewBroadcast":false,
      "isTelescoping":false
    },
    {"localName":"G194",
      "displayName": "赛琳娜",
      "deviceType":3,
      "isHotDevice":false,
      "isBleDevice": true,
      "madaCount":1,
      "isStrong":false,
      "isNewBroadcast":false,
      "isTelescoping":false
    },
    {"localName":"G353",
      "displayName": "元气鲸",
      "deviceType":3,
      "isHotDevice":false,
      "isBleDevice": true,
      "madaCount":1,
      "isStrong":false,
      "isNewBroadcast":false,
      "isTelescoping":false
    },
    {"localName":"G179",
      "displayName": "恒星飞机杯",
      "deviceType":2,
      "isHotDevice":true,
      "isBleDevice": true,
      "madaCount":1,
      "isStrong":false,
      "isNewBroadcast":false,
      "isTelescoping":false
    },
    {"localName":"B248",
      "displayName": "FF1飞机杯吮吸",
      "deviceType":1,
      "isHotDevice":true,
      "isBleDevice": true,
      "madaCount":2,
      "isStrong":false,
      "isNewBroadcast":false,
      "isTelescoping":false
    },
    {"localName":"B249",
      "displayName": "FF1飞机杯震动",
      "deviceType":1,
      "isHotDevice":true,
      "isBleDevice": true,
      "madaCount":2,
      "isStrong":false,
      "isNewBroadcast":false,
      "isTelescoping":false
    },
    {"localName":"G200",
      "displayName": "战士龟头训练器",
      "deviceType":1,
      "isHotDevice":true,
      "isBleDevice": true,
      "madaCount":2,
      "isStrong":false,
      "isNewBroadcast":false,
      "isTelescoping":false
    },
    {"localName":"B244",
      "displayName": "震极环",
      "deviceType":1,
      "isHotDevice":true,
      "isBleDevice": true,
      "madaCount":2,
      "isStrong":false,
      "isNewBroadcast":false,
      "isTelescoping":false
    },
    {"localName":"G195",
      "displayName": "觅唇训练器",
      "deviceType":1,
      "isHotDevice":false,
      "isBleDevice": true,
      "madaCount":2,
      "isStrong":false,
      "isNewBroadcast":false,
      "isTelescoping":false
    },
    {"localName":"B204",
      "displayName": "元气兔",
      "deviceType":1,
      "isHotDevice":true,
      "isBleDevice": true,
      "madaCount":2,
      "isStrong":false,
      "isNewBroadcast":false,
      "isTelescoping":false
    },
    {"localName":"B206",
      "displayName": "呼之欲兔Pro",
      "deviceType":1,
      "isHotDevice":true,
      "isBleDevice": true,
      "madaCount":2,
      "isStrong":false,
      "isNewBroadcast":false,
      "isTelescoping":false
    },
    {"localName":"B233",
      "displayName": "劲动",
      "deviceType":8,
      "isHotDevice":false,
      "isBleDevice": true,
      "madaCount":3,
      "isStrong":false,
      "isNewBroadcast":false,
      "isTelescoping":false
    },
    {"localName":"B232",
      "displayName": "灵动",
      "deviceType":8,
      "isHotDevice":false,
      "isBleDevice": true,
      "madaCount":3,
      "isStrong":false,
      "isNewBroadcast":false,
      "isTelescoping":false
    },
    {"localName":"B207",
      "displayName": "呼之欲兔Pro Max",
      "deviceType":8,
      "isHotDevice":false,
      "isBleDevice": true,
      "madaCount":3,
      "isStrong":false,
      "isNewBroadcast":false,
      "isTelescoping":false
    },
    {"localName":"B182",
      "displayName": "唇诱舌舔飞机杯",
      "deviceType":2,
      "isHotDevice":false,
      "isBleDevice": true,
      "madaCount":1,
      "isStrong":false,
      "isNewBroadcast":false,
      "isTelescoping":false
    },
    {"localName":"B258",
      "displayName": "虹吸飞机杯",
      "deviceType":2,
      "isHotDevice":false,
      "isBleDevice": true,
      "madaCount":1,
      "isStrong":false,
      "isNewBroadcast":false,
      "isTelescoping":false
    },
    {"localName":"B219",
      "displayName": "天玑飞机杯",
      "deviceType":1,
      "isHotDevice":false,
      "isBleDevice": true,
      "madaCount":2,
      "isStrong":false,
      "isNewBroadcast":false,
      "isTelescoping":false
    },
    {"localName":"B266",
      "displayName": "怪兽穿戴",
      "deviceType":1,
      "isHotDevice":false,
      "isBleDevice": true,
      "madaCount":2,
      "isStrong":false,
      "isNewBroadcast":false,
      "isTelescoping":false
    },
    {"localName":"B208",
      "displayName": "绮梦",
      "deviceType":8,
      "isHotDevice":false,
      "isBleDevice": true,
      "madaCount":3,
      "isStrong":false,
      "isNewBroadcast":false,
      "isTelescoping":false
    },
    {"localName":"B197",
      "displayName": "赫蒂/梦悦",
      "deviceType":0,
      "isHotDevice":true,
      "isBleDevice": true,
      "madaCount":1,
      "isStrong":false,
      "isNewBroadcast":false,
      "isTelescoping":false
    },
    {"localName":"B242",
      "displayName": "战士震环",
      "deviceType":0,
      "isHotDevice":true,
      "isBleDevice": true,
      "madaCount":1,
      "isStrong":false,
      "isNewBroadcast":false,
      "isTelescoping":false
    },
    {"localName":"B243",
      "displayName": "双珠震环",
      "deviceType":0,
      "isHotDevice":true,
      "isBleDevice": true,
      "madaCount":1,
      "isStrong":false,
      "isNewBroadcast":false,
      "isTelescoping":false
    },
    {"localName":"B202",
      "displayName": "诱可AV棒",
      "deviceType":0,
      "isHotDevice":true,
      "isBleDevice": true,
      "madaCount":1,
      "isStrong":false,
      "isNewBroadcast":false,
      "isTelescoping":false
    },
    {"localName":"B235",
      "displayName": "八爪鱼二代",
      "deviceType":0,
      "isHotDevice":true,
      "isBleDevice": true,
      "madaCount":1,
      "isStrong":false,
      "isNewBroadcast":false,
      "isTelescoping":false
    },
    {"localName":"G192",
      "displayName": "赛博引力飞机杯",
      "deviceType":0,
      "isHotDevice":false,
      "isBleDevice": true,
      "madaCount":1,
      "isStrong":false,
      "isNewBroadcast":false,
      "isTelescoping":false
    },
    {"localName":"B220",
      "displayName": "娆月",
      "deviceType":8,
      "isHotDevice":true,
      "isBleDevice": true,
      "madaCount":3,
      "isStrong":false,
      "isNewBroadcast":false,
      "isTelescoping":false
    },
    {"localName":"CX15",
      "displayName": "C型跳蛋",
      "deviceType":0,
      "isHotDevice":false,
      "isBleDevice": true,
      "madaCount":1,
      "isStrong":false,
      "isNewBroadcast":false,
      "isTelescoping":false
    },
    {"localName":"B223",
      "displayName": "珍妮电击",
      "deviceType":4,
      "isHotDevice":false,
      "isBleDevice": true,
      "madaCount":2,
      "isStrong":false,
      "isNewBroadcast":false,
      "isTelescoping":false
    },
    {"localName":"B234",
      "displayName": "萌小兔",
      "deviceType":0,
      "isHotDevice":false,
      "isBleDevice": true,
      "madaCount":1,
      "isStrong":false,
      "isNewBroadcast":false,
      "isTelescoping":false
    },
    {"localName":"B224",
      "displayName": "卡拉巴拉",
      "deviceType":0,
      "isHotDevice":false,
      "isBleDevice": true,
      "madaCount":1,
      "isStrong":false,
      "isNewBroadcast":false,
      "isTelescoping":false
    },
    {"localName":"B228",
      "displayName": "灵触",
      "deviceType":4,
      "isHotDevice":false,
      "isBleDevice": true,
      "madaCount":2,
      "isStrong":false,
      "isNewBroadcast":false,
      "isTelescoping":false
    },
    {"localName":"B229",
      "displayName": "赤吻",
      "deviceType":4,
      "isHotDevice":false,
      "isBleDevice": true,
      "madaCount":2,
      "isStrong":false,
      "isNewBroadcast":false,
      "isTelescoping":false
    },
    {"localName":"B255",
      "displayName": "枷笼",
      "deviceType":3,
      "isHotDevice":false,
      "isBleDevice": true,
      "madaCount":1,
      "isStrong":false,
      "isNewBroadcast":false,
      "isTelescoping":false
    },
    {"localName":"B222",
      "displayName": "小蕉友",
      "deviceType":1,
      "isHotDevice":false,
      "isBleDevice": true,
      "madaCount":2,
      "isStrong":false,
      "isNewBroadcast":false,
      "isTelescoping":false
    },
    {"localName":"B30A",
      "displayName": "绯吻",
      "deviceType":1,
      "isHotDevice":false,
      "isBleDevice": true,
      "madaCount":2,
      "isStrong":false,
      "isNewBroadcast":false,
      "isTelescoping":false
    },
    {"localName":"B30B",
      "displayName": "绯吻",
      "deviceType":1,
      "isHotDevice":false,
      "isBleDevice": true,
      "madaCount":2,
      "isStrong":false,
      "isNewBroadcast":false,
      "isTelescoping":false
    },
    {"localName":"B218",
      "displayName": "天鹅",
      "deviceType":0,
      "isHotDevice":false,
      "isBleDevice": true,
      "madaCount":1,
      "isStrong":false,
      "isNewBroadcast":false,
      "isTelescoping":false
    },
    {"localName":"B216",
      "displayName": "温妮",
      "deviceType":0,
      "isHotDevice":false,
      "isBleDevice": true,
      "madaCount":1,
      "isStrong":false,
      "isNewBroadcast":false,
      "isTelescoping":false
    },
    {"localName":"B240",
      "displayName": "极速飞机杯",
      "deviceType":0,
      "isHotDevice":false,
      "isBleDevice": true,
      "madaCount":1,
      "isStrong":false,
      "isNewBroadcast":false,
      "isTelescoping":false
    },
    {"localName":"196S",
      "displayName": "青提鸟吮吸",
      "deviceType":0,
      "isHotDevice":false,
      "isBleDevice": true,
      "madaCount":1,
      "isStrong":false,
      "isNewBroadcast":false,
      "isTelescoping":false
    },
    {"localName":"196V",
      "displayName": "青提鸟震动",
      "deviceType":0,
      "isHotDevice":true,
      "isBleDevice": true,
      "madaCount":1,
      "isStrong":false,
      "isNewBroadcast":false,
      "isTelescoping":false
    },
    {"localName":"B241",
      "displayName": "UFO飞机杯",
      "deviceType":1,
      "isHotDevice":true,
      "isBleDevice": true,
      "madaCount":2,
      "isStrong":false,
      "isNewBroadcast":false,
      "isTelescoping":false
    },
    {"localName":"B259",
      "displayName": "留声姬",
      "deviceType":0,
      "isHotDevice":true,
      "isBleDevice": true,
      "madaCount":1,
      "isStrong":false,
      "isNewBroadcast":false,
      "isTelescoping":false
    },
    {"localName":"B213",
      "displayName": "双翼机甲飞机杯",
      "deviceType":1,
      "isHotDevice":true,
      "isBleDevice": true,
      "madaCount":2,
      "isStrong":false,
      "isNewBroadcast":false,
      "isTelescoping":false
    },
    {"localName":"B236",
      "displayName": "MewZ 喵动",
      "deviceType":1,
      "isHotDevice":false,
      "isBleDevice": true,
      "madaCount":2,
      "isStrong":false,
      "isNewBroadcast":false,
      "isTelescoping":false
    },
    {"localName":"G189",
      "displayName": "红唇锁精环",
      "deviceType":1,
      "isHotDevice":false,
      "isBleDevice": true,
      "madaCount":2,
      "isStrong":false,
      "isNewBroadcast":false,
      "isTelescoping":false
    }
  ]
}

